chiga/__init__.py
chiga/cli.py
pp/__init__.py
pp/cli.py
chiga-0.1.dist-info/METADATA
chiga-0.1.dist-info/WHEEL
chiga-0.1.dist-info/entry_points.txt
chiga-0.1.dist-info/top_level.txt
chiga-0.1.dist-info/RECORD
