Metadata-Version: 2.1
Name: chiga
Version: 0.1
Summary: A custom package installer that manages requirements.txt
Home-page: https://github.com/CHiigaw/chiga
Author: AHMED FAHIM
Author-email: amhex01@gmail.com
